nonebot_plugin_couplets/__init__.py
nonebot_plugin_couplets-0.2.0.dist-info/LICENSE
nonebot_plugin_couplets-0.2.0.dist-info/METADATA
nonebot_plugin_couplets-0.2.0.dist-info/WHEEL
nonebot_plugin_couplets-0.2.0.dist-info/RECORD
