Metadata-Version: 2.1
Name: nonebot-plugin-couplets
Version: 0.2.0
Summary: Nonebot2对对联插件。
Home-page: https://github.com/CMHopeSunshine/nonebot-plugin-couplets
License: AGPL
Keywords: nonebot,nonebot2,couplets
Author: CMHopeSunshine
Author-email: 277073121@qq.com
Requires-Python: >=3.8,<4.0
Classifier: License :: Other/Proprietary License
Classifier: Programming Language :: Python :: 3
Classifier: Programming Language :: Python :: 3.8
Classifier: Programming Language :: Python :: 3.9
Classifier: Programming Language :: Python :: 3.10
Classifier: Programming Language :: Python :: 3.11
Requires-Dist: httpx (>=0.23.0,<0.24.0)
Requires-Dist: nonebot2 (>=2.0.0,<3.0.0)
